enum_properties/__init__.py
enum_properties/py.typed
enum_properties-2.4.1.dist-info/METADATA
enum_properties-2.4.1.dist-info/WHEEL
enum_properties-2.4.1.dist-info/licenses/LICENSE
enum_properties-2.4.1.dist-info/RECORD
