Metadata-Version: 2.4
Name: enum-properties
Version: 2.4.1
Summary: Add properties and method specializations to Python enumeration values with a simple declarative syntax.
Project-URL: Homepage, https://github.com/bckohan/enum-properties
Project-URL: Documentation, https://enum-properties.readthedocs.io
Project-URL: Repository, https://github.com/bckohan/enum-properties
Project-URL: Issues, https://github.com/bckohan/enum-properties/issues
Project-URL: Changelog, https://enum-properties.readthedocs.io/en/latest/changelog.html
Project-URL: Code_of_Conduct, https://github.com/bckohan/enum-properties/blob/main/CODE_OF_CONDUCT.md
Author-email: Brian Kohan <bckohan@gmail.com>
License-Expression: MIT
License-File: LICENSE
Keywords: dataclass,dataclasses,defines,enum,field,properties
Classifier: Development Status :: 5 - Production/Stable
Classifier: Environment :: Console
Classifier: Intended Audience :: Developers
Classifier: License :: OSI Approved :: MIT License
Classifier: Natural Language :: English
Classifier: Operating System :: OS Independent
Classifier: Programming Language :: Python
Classifier: Programming Language :: Python :: 3.9
Classifier: Programming Language :: Python :: 3.10
Classifier: Programming Language :: Python :: 3.11
Classifier: Programming Language :: Python :: 3.12
Classifier: Programming Language :: Python :: 3.13
Classifier: Programming Language :: Python :: 3.14
Classifier: Topic :: Software Development :: Libraries
Classifier: Topic :: Software Development :: Libraries :: Python Modules
Requires-Python: <4.0,>=3.9
